wwfdgroup1/__init__.py
wwfdgroup1/results.py
wwfdgroup1/test.py
wwfdgroup1-0.3.0.dist-info/LICENSE
wwfdgroup1-0.3.0.dist-info/METADATA
wwfdgroup1-0.3.0.dist-info/WHEEL
wwfdgroup1-0.3.0.dist-info/top_level.txt
wwfdgroup1-0.3.0.dist-info/RECORD
