Metadata-Version: 2.2
Name: wwfdgroup1
Version: 0.3.0
Summary: A package for displaying results
Author: Felix B.
Author-email: felixberner1@icloud.com
License: MIT
Classifier: Programming Language :: Python :: 3
Classifier: License :: OSI Approved :: MIT License
Classifier: Operating System :: OS Independent
License-File: LICENSE
Requires-Dist: pandas
